kero/__init__.py
kero/directory.py
kero/dummy.py
kero/pandas.py
kero/utils.py
kero-0.0.0.post2.dist-info/METADATA
kero-0.0.0.post2.dist-info/WHEEL
kero-0.0.0.post2.dist-info/licenses/LICENSE
kero-0.0.0.post2.dist-info/RECORD
